goose/__init__.py
goose/py.typed
goose_json-0.1.0.dist-info/METADATA
goose_json-0.1.0.dist-info/WHEEL
goose_json-0.1.0.dist-info/RECORD
