Metadata-Version: 2.4
Name: goose-json
Version: 0.1.0
Summary: A library for conveniently navigating unstructured blobs of data.
Author-email: Tom Fryers <t.fryers@gmail.com>
Requires-Python: >=3.12
